know_the_time/__init__.py
know_the_time/know_the_time.py
know_the_time-0.0.8.dist-info/licenses/LICENSE
know_the_time-0.0.8.dist-info/METADATA
know_the_time-0.0.8.dist-info/WHEEL
know_the_time-0.0.8.dist-info/top_level.txt
know_the_time-0.0.8.dist-info/RECORD
